[
  {
    "id": "1",
    "email": "aaa",
    "password": "1111",
    "fio": "Андреев Андрей Андреевич",
    "roles": ["user"],

    "places": [
      {
        "id": 3,
        "name": "Алексеевский район"
      },
      {
        "id": 4,
        "name": "«Станция  юных техников» Алексеевского городского округа"
      }
    ]
  },
  {
    "id": "2",
    "email": "katya@mail.ru",
    "password": "1901",
    "fio": "Екатерина Ходячих",
    "roles": ["user"],
    "places": [
      {
        "id": 1,
        "name": "Белгородский район"
      },
      {
        "id": 2,
        "name": "УДО Белгород"
      }
    ]
  },
  {
    "id": "3",
    "email": "iii",
    "password": "2222",
    "fio": "Иванова Татьяна Викторовна",
    "roles": ["user", "admin"],
    "places": [
      {
        "id": 1,
        "name": "Белгородский район"
      },
      {
        "id": 2,
        "name": "УДО Белгород"
      }
    ]
  },
  {
    "id": "4",
    "email": "masha@mail.ru",
    "password": "0401",
    "fio": "Ходячих Мария",
    "roles": ["admin"],
    "places": []
  }
]
